flake8_assert_msg/__init__.py
flake8_assert_msg/flake8_assert_msg.py
flake8_assert_msg/version.py
flake8_assert_msg-1.1.1.dist-info/LICENSE
flake8_assert_msg-1.1.1.dist-info/METADATA
flake8_assert_msg-1.1.1.dist-info/WHEEL
flake8_assert_msg-1.1.1.dist-info/entry_points.txt
flake8_assert_msg-1.1.1.dist-info/top_level.txt
flake8_assert_msg-1.1.1.dist-info/RECORD
