Metadata-Version: 2.1
Name: flake8-assert-msg
Version: 1.1.1
Summary: flake8 plugin which forbids assert statements without messages
Home-page: https://github.com/rkm/flake8-assert-msg
Author: Ruairidh MacLeod
Author-email: ruairidh@rkm.dev
License: MIT
Platform: UNKNOWN
Classifier: License :: OSI Approved :: MIT License
Classifier: Programming Language :: Python :: 3
Classifier: Programming Language :: Python :: 3 :: Only
Classifier: Programming Language :: Python :: 3.6
Classifier: Programming Language :: Python :: 3.7
Classifier: Programming Language :: Python :: 3.8
Requires-Python: >=3.6
Requires-Dist: flake8 (>=3.7)
